BiopythonJiaochengYuShouce/README.md
BiopythonJiaochengYuShouce/__init__.py
BiopythonJiaochengYuShouce/__main__.py
BiopythonJiaochengYuShouce/file.epub
BiopythonJiaochengYuShouce/index.html
BiopythonJiaochengYuShouce/css/__init__.py
BiopythonJiaochengYuShouce/css/annotations.css
BiopythonJiaochengYuShouce/css/main.css
BiopythonJiaochengYuShouce/css/normalize.css
BiopythonJiaochengYuShouce/css/popup.css
BiopythonJiaochengYuShouce/font/__init__.py
BiopythonJiaochengYuShouce/font/fontello.eot
BiopythonJiaochengYuShouce/font/fontello.svg
BiopythonJiaochengYuShouce/font/fontello.ttf
BiopythonJiaochengYuShouce/font/fontello.woff
BiopythonJiaochengYuShouce/img/__init__.py
BiopythonJiaochengYuShouce/img/annotator-glyph-sprite.png
BiopythonJiaochengYuShouce/img/annotator-icon-sprite.png
BiopythonJiaochengYuShouce/img/apple-touch-icon.png
BiopythonJiaochengYuShouce/img/cancelfullscreen.png
BiopythonJiaochengYuShouce/img/close.png
BiopythonJiaochengYuShouce/img/fullscreen.png
BiopythonJiaochengYuShouce/img/loader.gif
BiopythonJiaochengYuShouce/img/menu-icon.png
BiopythonJiaochengYuShouce/img/save.png
BiopythonJiaochengYuShouce/img/saved.png
BiopythonJiaochengYuShouce/img/settings-s.png
BiopythonJiaochengYuShouce/img/settings.png
BiopythonJiaochengYuShouce/img/star.png
BiopythonJiaochengYuShouce/js/__init__.py
BiopythonJiaochengYuShouce/js/epub.js
BiopythonJiaochengYuShouce/js/epub.min.js
BiopythonJiaochengYuShouce/js/epub.min.map
BiopythonJiaochengYuShouce/js/hooks.min.js
BiopythonJiaochengYuShouce/js/hooks.min.map
BiopythonJiaochengYuShouce/js/reader.js
BiopythonJiaochengYuShouce/js/reader.js.map
BiopythonJiaochengYuShouce/js/reader.min.js
BiopythonJiaochengYuShouce/js/reader.min.map
BiopythonJiaochengYuShouce/js/hooks/__init__.py
BiopythonJiaochengYuShouce/js/hooks/extensions/__init__.py
BiopythonJiaochengYuShouce/js/hooks/extensions/highlight.js
BiopythonJiaochengYuShouce/js/libs/__init__.py
BiopythonJiaochengYuShouce/js/libs/jquery.min.js
biopython_jiaocheng_yu_shouce-2024.3.2.0.dist-info/METADATA
biopython_jiaocheng_yu_shouce-2024.3.2.0.dist-info/WHEEL
biopython_jiaocheng_yu_shouce-2024.3.2.0.dist-info/entry_points.txt
biopython_jiaocheng_yu_shouce-2024.3.2.0.dist-info/top_level.txt
biopython_jiaocheng_yu_shouce-2024.3.2.0.dist-info/RECORD
